{
"type": "FeatureCollection",
"name": "puntos_interes_medellin_emergency_ambulance_station",
"crs": { "type": "name", "properties": { "name": "urn:ogc:def:crs:OGC:1.3:CRS84" } },
"features": [
{ "type": "Feature", "properties": { "element_type": "node", "osmid": 7348952147, "emergency": "ambulance_station", "name": "Emergencias apolo medellin" }, "geometry": { "type": "Point", "coordinates": [ -75.5672181, 6.3089202 ] } }
]
}
